transaud/__init__.py
transaud/audio_converter.py
transaud/cli.py
transaud/diarizer.py
transaud/env.py
transaud/utils.py
transaud/whisper.py
transaud-0.1.0.dist-info/LICENSE
transaud-0.1.0.dist-info/METADATA
transaud-0.1.0.dist-info/WHEEL
transaud-0.1.0.dist-info/entry_points.txt
transaud-0.1.0.dist-info/RECORD
