Metadata-Version: 2.3
Name: transaud
Version: 0.1.0
Summary: audio diarizer and automatic speech recognition cli tool
License: MIT
Author: Joses
Requires-Python: >=3.11,<3.14
Classifier: License :: OSI Approved :: MIT License
Classifier: Programming Language :: Python :: 3
Classifier: Programming Language :: Python :: 3.11
Classifier: Programming Language :: Python :: 3.12
Classifier: Programming Language :: Python :: 3.13
Requires-Dist: click (>=8.3.1,<9.0.0)
Requires-Dist: dotenv (>=0.9.9,<0.10.0)
Requires-Dist: loguru (>=0.7.3,<0.8.0)
Requires-Dist: pyannote-audio (>=4.0.3,<5.0.0)
Requires-Dist: pydub (>=0.25.1,<0.26.0)
Requires-Dist: torch (==2.8.0)
Requires-Dist: tqdm (>=4.67.1,<5.0.0)
Requires-Dist: transformers (>=4.57.3,<5.0.0)
